[{"date":"2013-05-15T13:38:20.000Z","total":{"sloc":439,"maintainability":190.42256902863696},"average":{"sloc":146,"maintainability":"63.47"}},{"date":"2013-05-25T00:19:01.000Z","total":{"sloc":1019,"maintainability":464.7004688576052},"average":{"sloc":169,"maintainability":"77.45"}},{"date":"2013-05-27T20:40:57.000Z","total":{"sloc":1350,"maintainability":684.5973995917908},"average":{"sloc":150,"maintainability":"76.07"}},{"date":"2013-05-30T00:05:41.000Z","total":{"sloc":1420,"maintainability":677.6157370683444},"average":{"sloc":157,"maintainability":"75.29"}},{"date":"2013-06-03T03:31:37.000Z","total":{"sloc":1594,"maintainability":660.0113082155028},"average":{"sloc":177,"maintainability":"73.33"}},{"date":"2013-06-08T02:06:00.000Z","total":{"sloc":1914,"maintainability":814.459580927916},"average":{"sloc":174,"maintainability":"74.04"}},{"date":"2013-09-09T00:08:25.000Z","total":{"sloc":2215,"maintainability":956.5029362038994},"average":{"sloc":170,"maintainability":"73.58"}},{"date":"2013-09-11T05:11:47.000Z","total":{"sloc":2406,"maintainability":1036.8172427187371},"average":{"sloc":171,"maintainability":"74.06"}},{"date":"2013-09-19T03:05:03.000Z","total":{"sloc":2511,"maintainability":1031.6721626668868},"average":{"sloc":179,"maintainability":"73.69"}},{"date":"2013-09-21T05:23:14.000Z","total":{"sloc":2854,"maintainability":1104.247783039583},"average":{"sloc":190,"maintainability":"73.62"}},{"date":"2013-10-03T19:43:01.000Z","total":{"sloc":3166,"maintainability":1104.4322839363397},"average":{"sloc":211,"maintainability":"73.63"}},{"date":"2013-11-03T02:42:19.000Z","total":{"sloc":3203,"maintainability":1103.155601999895},"average":{"sloc":213,"maintainability":"73.54"}},{"date":"2014-03-28T19:53:33.000Z","total":{"sloc":3509,"maintainability":1104.5133151012585},"average":{"sloc":233,"maintainability":"73.63"}},{"date":"2015-01-14T22:57:13.000Z","total":{"sloc":3598,"maintainability":1246.3426212278202},"average":{"sloc":211,"maintainability":"73.31"}},{"date":"2015-02-15T17:18:29.000Z","total":{"sloc":3913,"maintainability":1538.5495358369199},"average":{"sloc":186,"maintainability":"73.26"}},{"date":"2015-02-27T06:33:15.000Z","total":{"sloc":3948,"maintainability":1632.1290647440983},"average":{"sloc":179,"maintainability":"74.19"}},{"date":"2015-03-05T13:41:32.000Z","total":{"sloc":4024,"maintainability":1624.3593934326943},"average":{"sloc":182,"maintainability":"73.83"}},{"date":"Thu, 02 Apr 2015 20:35:49 GMT","total":{"sloc":4398,"maintainability":1838.8380721190913},"average":{"sloc":175,"maintainability":"73.55"}},{"date":"Fri, 03 Apr 2015 18:12:25 GMT","total":{"sloc":4444,"maintainability":1840.768285470808},"average":{"sloc":177,"maintainability":"73.63"}},{"date":"Mon, 06 Apr 2015 22:10:20 GMT","total":{"sloc":4443,"maintainability":1840.9330149107948},"average":{"sloc":177,"maintainability":"73.64"}},{"date":"Mon, 06 Apr 2015 23:48:34 GMT","total":{"sloc":4481,"maintainability":1920.2716585215123},"average":{"sloc":172,"maintainability":"73.86"}},{"date":"Tue, 07 Apr 2015 01:18:31 GMT","total":{"sloc":4481,"maintainability":1920.2716585215123},"average":{"sloc":172,"maintainability":"73.86"}},{"date":"Wed, 08 Apr 2015 17:14:01 GMT","total":{"sloc":4483,"maintainability":1920.2645628181065},"average":{"sloc":172,"maintainability":"73.86"}},{"date":"Wed, 20 May 2015 21:52:52 GMT","total":{"sloc":4483,"maintainability":1920.2645628181065},"average":{"sloc":172,"maintainability":"73.86"}},{"date":"Thu, 28 May 2015 05:07:47 GMT","total":{"sloc":4497,"maintainability":1923.5645294290666},"average":{"sloc":172,"maintainability":"73.98"}}]